infi.wioctl-0.1.15-py2.7-nspkg.pth
infi/wioctl/__init__.py
infi/wioctl/__version__.py
infi/wioctl/api.py
infi/wioctl/constants.py
infi/wioctl/errors.py
infi/wioctl/structures.py
infi.wioctl-0.1.15.dist-info/LICENSE
infi.wioctl-0.1.15.dist-info/METADATA
infi.wioctl-0.1.15.dist-info/WHEEL
infi.wioctl-0.1.15.dist-info/entry_points.txt
infi.wioctl-0.1.15.dist-info/namespace_packages.txt
infi.wioctl-0.1.15.dist-info/top_level.txt
infi.wioctl-0.1.15.dist-info/RECORD
