Metadata-Version: 2.1
Name: infi.wioctl
Version: 0.1.15
Summary: Windows ioctl wrapper
Home-page: https://github.com/Infinidat/infi.wioctl
Author: Arnon Yaari
Author-email: arnony@infinidat.com
License: BSD
Platform: UNKNOWN
Classifier: Intended Audience :: Developers
Classifier: Intended Audience :: System Administrators
Classifier: License :: OSI Approved :: BSD License
Classifier: Operating System :: OS Independent
Classifier: Programming Language :: Python
Classifier: Programming Language :: Python :: 2
Classifier: Programming Language :: Python :: 3
Classifier: Topic :: Software Development :: Libraries :: Python Modules
Requires-Dist: infi.cwrap
Requires-Dist: infi.instruct
Requires-Dist: setuptools
